saldo/__init__.py
saldo/lib/libsaldo.so
saldo/lib/ext_libs/libHSStateVar-1.2.2-8Hv9klK7mv0HId52XsoM7J-ghc9.4.7.so
saldo/lib/ext_libs/libHSarray-0.5.4.0-ghc9.4.7.so
saldo/lib/ext_libs/libHSbase-4.17.2.0-ghc9.4.7.so
saldo/lib/ext_libs/libHSbase-orphans-0.9.0-F4sAk472rtiErTEcIfunNV-ghc9.4.7.so
saldo/lib/ext_libs/libHSbifunctors-5.5.15-36VTthxX2GmINzxvsrkAS1-ghc9.4.7.so
saldo/lib/ext_libs/libHSbinary-0.8.9.1-ghc9.4.7.so
saldo/lib/ext_libs/libHSbytestring-0.11.5.2-ghc9.4.7.so
saldo/lib/ext_libs/libHScomonad-5.0.8-DDhVCrhgoTZ62NhaLEUFvL-ghc9.4.7.so
saldo/lib/ext_libs/libHScontainers-0.6.7-ghc9.4.7.so
saldo/lib/ext_libs/libHScontravariant-1.5.5-6ScqY0S45R1AWbvfs82K9X-ghc9.4.7.so
saldo/lib/ext_libs/libHSdeepseq-1.4.8.0-ghc9.4.7.so
saldo/lib/ext_libs/libHSdistributive-0.6.2.1-5KEtLCIZxurBM28L7Cg4Rw-ghc9.4.7.so
saldo/lib/ext_libs/libHSfilepath-1.4.2.2-ghc9.4.7.so
saldo/lib/ext_libs/libHSghc-bignum-1.3-ghc9.4.7.so
saldo/lib/ext_libs/libHSghc-boot-th-9.4.7-ghc9.4.7.so
saldo/lib/ext_libs/libHSghc-prim-0.9.1-ghc9.4.7.so
saldo/lib/ext_libs/libHShashable-1.4.3.0-D7UsbjzS63CIL9MHK13cOI-ghc9.4.7.so
saldo/lib/ext_libs/libHShashtables-1.3.1-CpxaEAM7GGX7htWRGUscK2-ghc9.4.7.so
saldo/lib/ext_libs/libHSindexed-traversable-0.1.2.1-4MWkBnFErvq3PVvZRvlACO-ghc9.4.7.so
saldo/lib/ext_libs/libHSinvariant-0.6.2-GLS4K9k65wE7OiiWQGt3u4-ghc9.4.7.so
saldo/lib/ext_libs/libHSpretty-1.1.3.6-ghc9.4.7.so
saldo/lib/ext_libs/libHSprimitive-0.8.0.0-LlEyZnmQ2mlGS0nNflVSqQ-ghc9.4.7.so
saldo/lib/ext_libs/libHSprofunctors-5.6.2-4Cvn9Hd9ts7GIwGjgfUnkA-ghc9.4.7.so
saldo/lib/ext_libs/libHSrts-1.0.2-ghc9.4.7.so
saldo/lib/ext_libs/libHSstm-2.5.1.0-ghc9.4.7.so
saldo/lib/ext_libs/libHStagged-0.8.7-GN1x2L1RHnXCDXt20e1uDE-ghc9.4.7.so
saldo/lib/ext_libs/libHStemplate-haskell-2.19.0.0-ghc9.4.7.so
saldo/lib/ext_libs/libHStext-2.0.2-ghc9.4.7.so
saldo/lib/ext_libs/libHSth-abstraction-0.4.5.0-CynkUuS8OuAKbGjDnje1Fs-ghc9.4.7.so
saldo/lib/ext_libs/libHStransformers-0.5.6.2-ghc9.4.7.so
saldo_python-0.0.2.dist-info/METADATA
saldo_python-0.0.2.dist-info/WHEEL
saldo_python-0.0.2.dist-info/top_level.txt
saldo_python-0.0.2.dist-info/RECORD
